aquilax/__init__.py
aquilax/__main__.py
aquilax/client.py
aquilax/config.py
aquilax/index.py
aquilax/logger.py
aquilax-1.3.14.dist-info/licenses/LICENSE
aquilax-1.3.14.dist-info/METADATA
aquilax-1.3.14.dist-info/WHEEL
aquilax-1.3.14.dist-info/entry_points.txt
aquilax-1.3.14.dist-info/top_level.txt
aquilax-1.3.14.dist-info/RECORD
