Metadata-Version: 2.4
Name: aquilax
Version: 1.3.14
Summary: AquilaX CLI Client
Author-email: Omer <admin@aquilax.io>
License-Expression: Apache-2.0
Project-URL: Homepage, https://github.com/AquilaX-AI/AquilaX-Client
Classifier: Programming Language :: Python :: 3
Classifier: Operating System :: OS Independent
Requires-Python: >=3.6
License-File: LICENSE
Requires-Dist: requests
Requires-Dist: python-dotenv
Requires-Dist: requests-toolbelt
Requires-Dist: tabulate
Requires-Dist: colorama
Dynamic: license-file
